Workbook

Sheet Raw
B3: Year | C3: Revenue | D3: Users | E3: Operating expenses | F3: Operating profit / (loss) | G3: Net income | H3: Employees
B4: 2020 | C4: 222142000 | D4: 14500000 | E4: 225697000 | F4: -200649000 | G4: -106938000 | H4: 2200
B5: 2021 | C5: 636000000 | D5: 16420000 | E5: 309000000 | F5: 59100000 | G5: 26000000 | H5: 5000
B6: 2022 | C6: 922547000 | D6: 26200000 | E6: 667076000 | F6: -25418000 | G6: 5802000 | H6: 5913
B7: 2023 | C7: 1797890000 | D7: 38000000 | E7: 932752000 | F7: 437828000 | G7: 344075000 | H7: 8152
B8: 2024 | C8: 3090043000 | D8: 45000000 | E8: 1400412000 | F8: 1088730000 | G8: 790426000 | H8: 10000

Sheet Growth
B3: Year | C3: Revenue | D3: Users | E3: Revenue YoY | F3: Users YoY | G3: Revenue Index | H3: Users Index
B4: 2020 | C4: 222142000 | D4: 14500000 | E4: - | F4: - | G4: 100 | H4: 100
B5: 2021 | C5: 636000000 | D5: 16420000 | E5: =C5/C4-1 -> 1.8630336 | F5: =D5/D4-1 -> 0.13241379 | G5: =C5/$C$4*100 -> 286.30336 | H5: =D5/$D$4*100 -> 113.24138
B6: 2022 | C6: 922547000 | D6: 26200000 | E6: =C6/C5-1 -> 0.4505456 | F6: =D6/D5-1 -> 0.5956151 | G6: =C6/$C$4*100 -> 415.29607 | H6: =D6/$D$4*100 -> 180.68966
B7: 2023 | C7: 1797890000 | D7: 38000000 | E7: =C7/C6-1 -> 0.94883296 | F7: =D7/D6-1 -> 0.45038168 | G7: =C7/$C$4*100 -> 809.34267 | H7: =D7/$D$4*100 -> 262.06897
B8: 2024 | C8: 3090043000 | D8: 45000000 | E8: =C8/C7-1 -> 0.71870526 | F8: =D8/D7-1 -> 0.18421053 | G8: =C8/$C$4*100 -> 1391.0215 | H8: =D8/$D$4*100 -> 310.34483
B10: Revenue CAGR
B11: =(C8/C4)^(1/4)-1 -> 0.93122761
B12: Users CAGR
B13: =(D8/D4)^(1/4)-1 -> 0.32727565

Sheet ARPU
B3: Year | C3: Revenue | D3: Users | E3: Avg Users | F3: ARPU | G3: ARPU YoY
B4: 2020 | C4: 222142000 | D4: 14500000 | E4: =D4 -> 14500000 | F4: =C4/D4 -> 15.320138 | G4: -
B5: 2021 | C5: 636000000 | D5: 16420000 | E5: =(D5+D4)/2 -> 15460000 | F5: =C5/D5 -> 38.733252 | G5: =F5/F4-1 -> 1.5282574
B6: 2022 | C6: 922547000 | D6: 26200000 | E6: =(D6+D5)/2 -> 21310000 | F6: =C6/D6 -> 35.211718 | G6: =F6/F5-1 -> -0.090917606
B7: 2023 | C7: 1797890000 | D7: 38000000 | E7: =(D7+D6)/2 -> 32100000 | F7: =C7/D7 -> 47.312895 | G7: =F7/F6-1 -> 0.34366904
B8: 2024 | C8: 3090043000 | D8: 45000000 | E8: =(D8+D7)/2 -> 41500000 | F8: =C8/D8 -> 68.667622 | G8: =F8/F7-1 -> 0.45135111

Sheet Incremental
B3: Year | C3: Revenue | D3: Users | E3: ΔRevenue | F3: ΔUsers | G3: ARPU | H3: Incremental ARPU
B4: 2020 | C4: 222142000 | D4: 14500000 | E4: - | F4: - | G4: =ARPU!F4 -> 15.320138
B5: 2021 | C5: 636000000 | D5: 16420000 | E5: =C5-C4 -> 413858000 | F5: =D5-D4 -> 1920000 | G5: =ARPU!F5 -> 38.733252 | H5: =E5/F5 -> 215.55104
B6: 2022 | C6: 922547000 | D6: 26200000 | E6: =C6-C5 -> 286547000 | F6: =D6-D5 -> 9780000 | G6: =ARPU!F6 -> 35.211718 | H6: =E6/F6 -> 29.299284
B7: 2023 | C7: 1797890000 | D7: 38000000 | E7: =C7-C6 -> 875343000 | F7: =D7-D6 -> 11800000 | G7: =ARPU!F7 -> 47.312895 | H7: =E7/F7 -> 74.18161
B8: 2024 | C8: 3090043000 | D8: 45000000 | E8: =C8-C7 -> 1292153000 | F8: =D8-D7 -> 7000000 | G8: =ARPU!F8 -> 68.667622 | H8: =E8/F8 -> 184.59329

Sheet Costs
B3: Year | C3: Revenue | D3: Operating expenses | E3: Opex YoY | F3: Opex / Revenue | G3: Operating margin
B4: 2020 | C4: 222142000 | D4: 225697000 | E4: - | F4: =D4/C4 -> 1.0160033 | G4: =1-F4 -> -0.016003277
B5: 2021 | C5: 636000000 | D5: 309000000 | E5: =D5/D4-1 -> 0.36909219 | F5: =D5/C5 -> 0.48584906 | G5: =1-F5 -> 0.51415094
B6: 2022 | C6: 922547000 | D6: 667076000 | E6: =D6/D5-1 -> 1.158822 | F6: =D6/C6 -> 0.72308078 | G6: =1-F6 -> 0.27691922
B7: 2023 | C7: 1797890000 | D7: 932752000 | E7: =D7/D6-1 -> 0.39826946 | F7: =D7/C7 -> 0.51880371 | G7: =1-F7 -> 0.48119629
B8: 2024 | C8: 3090043000 | D8: 1400412000 | E8: =D8/D7-1 -> 0.50137657 | F8: =D8/C8 -> 0.45320146 | G8: =1-F8 -> 0.54679854

Sheet Unit Economics
B3: Year | C3: Revenue | D3: Operating expenses | E3: Employees | F3: Revenue / Employee | G3: Opex / Employee
B4: 2020 | C4: 222142000 | D4: 225697000 | E4: 2200 | F4: =C4/E4 -> 100973.64 | G4: =D4/E4 -> 102589.55
B5: 2021 | C5: 636000000 | D5: 309000000 | E5: 5000 | F5: =C5/E5 -> 127200 | G5: =D5/E5 -> 61800
B6: 2022 | C6: 922547000 | D6: 667076000 | E6: 5913 | F6: =C6/E6 -> 156020.13 | G6: =D6/E6 -> 112815.15
B7: 2023 | C7: 1797890000 | D7: 932752000 | E7: 8152 | F7: =C7/E7 -> 220545.88 | G7: =D7/E7 -> 114420.02
B8: 2024 | C8: 3090043000 | D8: 1400412000 | E8: 10000 | F8: =C8/E8 -> 309004.3 | G8: =D8/E8 -> 140041.2

Sheet Valuation
B3: Metric | C3: Value
B4: Revenue (2024) | C4: 3090
B5: Assumed EV / Revenue | C5: 8.0x
B6: Implied Enterprise Value | C6: 24720
B9: EV / Revenue | C9: EV (£bn)
B10: 6x | C10: 18.5
B11: 8x | C11: 24.7
B12: 10x | C12: 30.9
B14: Assumptions
B15: Implied Revenue in Year 5 | C15: =C18/10/C20 -> 10000000000
B16: Implied Revenue CAGR | C16: =(C15/Raw!C8)^(1/5)-1 -> 0.26475701
B18: Current EV: | C18: 25000000000
B19: Current Revenue: | C19: 3100000000
B20: Target margin | C20: 0.25
B21: Horizon: | C21: 5
B22: Discount rate (proxy) | C22: 0.1
B24: ARPU × Users sanity check
B26: Metric | C26: Value
B27: Users (2024) | C27: 45000000
B28: ARPU (2024) | C28: 69
B29: Revenue (calc) | C29: 3100000000

Sheet Cash_Flow
B3: Year | C3: Revenue | D3: Operating profit | E3: Core Op CF | F3: Reported CFO | G3: Core CF margin | H3: Core CF / Operating profit
B4: 2020 | C4: 222142 | D4: -200649 | E4: -126222 | F4: 2195162 | G4: =E4/C4 -> -0.56820412 | H4: =IF(D4>0,E4/D4,NA()) -> #N/A
B5: 2021 | C5: 636000 | D5: 59091 | E5: 150980 | F5: 2764283 | G5: =E5/C5 -> 0.23738994 | H5: =IF(D5>0,E5/D5,NA()) -> 2.5550422
B6: 2022 | C6: 922547 | D6: -25418 | E6: -107932 | F6: 4760661 | G6: =E6/C6 -> -0.1169935 | H6: =IF(D6>0,E6/D6,NA()) -> #N/A
B7: 2023 | C7: 1797890 | D7: 437828 | E7: 593529 | F7: 2955169 | G7: =E7/C7 -> 0.33012531 | H7: =IF(D7>0,E7/D7,NA()) -> 1.3556214
B8: 2024 | C8: 3090043 | D8: 1088730 | E8: 1504941 | F8: 8123558 | G8: =E8/C8 -> 0.48702914 | H8: =IF(D8>0,E8/D8,NA()) -> 1.3822904
